MANIFEST.in
setup.py
anthill/promo/__init__.py
anthill/promo/admin.py
anthill/promo/handlers.py
anthill/promo/options.py
anthill/promo/server.py
anthill/promo/model/__init__.py
anthill/promo/model/content.py
anthill/promo/model/promo.py
anthill/promo/sql/promo_code.sql
anthill/promo/sql/promo_code_users.sql
anthill/promo/sql/promo_contents.sql
anthill_promo.egg-info/PKG-INFO
anthill_promo.egg-info/SOURCES.txt
anthill_promo.egg-info/dependency_links.txt
anthill_promo.egg-info/namespace_packages.txt
anthill_promo.egg-info/not-zip-safe
anthill_promo.egg-info/requires.txt
anthill_promo.egg-info/top_level.txt