Metadata-Version: 1.0
Name: anthill-promo
Version: 0.2
Summary: Promo codes service for Anthill platform
Home-page: https://github.com/anthill-platform/anthill-promo
Author: desertkun
Author-email: desertkun@gmail.com
License: MIT
Platform: UNKNOWN
